fragaria/__init__.py
fragaria/cli.py
fragaria/config.yaml
fragaria/core/__init__.py
fragaria/core/config.yaml
fragaria/core/core.py
fragaria/frontend/.gitignore
fragaria/frontend/README.md
fragaria/frontend/package-lock.json
fragaria/frontend/package.json
fragaria/frontend/public/favicon.png
fragaria/frontend/public/global.css
fragaria/frontend/public/index.html
fragaria/frontend/rollup.config.js
fragaria/frontend/scripts/setupTypeScript.js
fragaria/frontend/src/App.svelte
fragaria/frontend/src/main.js
fragaria/main.py
fragaria/setup.py
fragaria-0.1.2.dist-info/LICENSE
fragaria-0.1.2.dist-info/METADATA
fragaria-0.1.2.dist-info/WHEEL
fragaria-0.1.2.dist-info/entry_points.txt
fragaria-0.1.2.dist-info/RECORD
