Metadata-Version: 2.3
Name: fragaria
Version: 0.1.2
Summary: Advanced Chain of Thought (CoT) Reasoning API with Reinforcement Learning (RL)
License: MIT
Keywords: ai,llm,chain-of-thought,reinforcement-learning,reasoning
Author: Dipankar Sarkar
Author-email: me@dipankar.name
Requires-Python: >=3.11,<4.0
Classifier: Development Status :: 3 - Alpha
Classifier: Intended Audience :: Developers
Classifier: License :: OSI Approved :: MIT License
Classifier: Programming Language :: Python :: 3
Classifier: Programming Language :: Python :: 3.11
Classifier: Programming Language :: Python :: 3.12
Classifier: Programming Language :: Python :: 3.13
Requires-Dist: aiofiles (>=24.1.0,<25.0.0)
Requires-Dist: aiohttp (>=3.10.5,<4.0.0)
Requires-Dist: fastapi (>=0.114.2,<0.115.0)
Requires-Dist: openai (>=1.45.0,<2.0.0)
Requires-Dist: pydantic (>=2.9.1,<3.0.0)
Requires-Dist: pyyaml (>=6.0.2,<7.0.0)
Requires-Dist: uvicorn (>=0.30.6,<0.31.0)
Project-URL: Bug Tracker, https://github.com/terraprompt/fragaria/issues
Project-URL: Repository, https://github.com/terraprompt/fragaria
